{
  "main": {
    "id": "e8c3a6ad0fe7b0c5",
    "type": "split",
    "children": [
      {
        "id": "259ddcd5a4941724",
        "type": "tabs",
        "children": [
          {
            "id": "d92c63d0fe27e040",
            "type": "leaf",
            "pane-relief:history-v1": {
              "pos": 26,
              "stack": [
                {
                  "title": "Rat der Europäischen Union (Ministerrat)",
                  "icon": "lucide-file",
                  "state": "{\"type\":\"markdown\",\"state\":{\"file\":\"Sowi/Rat der Europäischen Union (Ministerrat).md\",\"mode\":\"source\",\"backlinks\":true,\"source\":false}}",
                  "eState": "{\"cursor\":{\"from\":{\"line\":31,\"ch\":27},\"to\":{\"line\":31,\"ch\":27}},\"scroll\":5.38673285198556}"
                },
                {
                  "title": "Europäische Union",
                  "icon": "lucide-file",
                  "state": "{\"type\":\"markdown\",\"state\":{\"file\":\"Sowi/Europäische Union.md\",\"mode\":\"source\",\"backlinks\":true,\"source\":false}}",
                  "eState": "{\"cursor\":{\"from\":{\"line\":0,\"ch\":0},\"to\":{\"line\":0,\"ch\":0}},\"scroll\":0.7843137254901961}"
                },
                {
                  "title": "Europäische Union - Phasen",
                  "icon": "lucide-file",
                  "state": "{\"type\":\"markdown\",\"state\":{\"file\":\"Sowi/Europäische Union - Phasen.md\",\"mode\":\"source\",\"backlinks\":true,\"source\":false}}",
                  "eState": "{\"cursor\":{\"from\":{\"line\":0,\"ch\":7},\"to\":{\"line\":0,\"ch\":7}},\"scroll\":0}"
                },
                {
                  "title": "Eintritt des Westbalkans in die EU",
                  "icon": "lucide-file",
                  "state": "{\"type\":\"markdown\",\"state\":{\"file\":\"Sowi/Eintritt des Westbalkans in die EU.md\",\"mode\":\"source\",\"backlinks\":true,\"source\":false}}",
                  "eState": "{\"cursor\":{\"from\":{\"line\":0,\"ch\":0},\"to\":{\"line\":0,\"ch\":0}}}"
                },
                {
                  "title": "Europäische Gemeinschaft für Kohle und Stahl",
                  "icon": "lucide-file",
                  "state": "{\"type\":\"markdown\",\"state\":{\"file\":\"Sowi/Europäische Gemeinschaft für Kohle und Stahl.md\",\"mode\":\"source\",\"backlinks\":true,\"source\":false}}",
                  "eState": "{\"cursor\":{\"from\":{\"line\":0,\"ch\":0},\"to\":{\"line\":0,\"ch\":0}}}"
                },
                {
                  "title": "Europäische Union - Phasen",
                  "icon": "lucide-file",
                  "state": "{\"type\":\"markdown\",\"state\":{\"file\":\"Sowi/Europäische Union - Phasen.md\",\"mode\":\"source\",\"backlinks\":true,\"source\":false}}",
                  "eState": "{\"cursor\":{\"from\":{\"line\":0,\"ch\":0},\"to\":{\"line\":0,\"ch\":0}}}"
                },
                {
                  "title": "Europäische Union - Friedensnobelpreis",
                  "icon": "lucide-file",
                  "state": "{\"type\":\"markdown\",\"state\":{\"file\":\"Sowi/Europäische Union - Friedensnobelpreis.md\",\"mode\":\"source\",\"backlinks\":true,\"source\":false}}",
                  "eState": "{\"cursor\":{\"from\":{\"line\":0,\"ch\":0},\"to\":{\"line\":0,\"ch\":0}}}"
                },
                {
                  "title": "Europäische Union - Phasen",
                  "icon": "lucide-file",
                  "state": "{\"type\":\"markdown\",\"state\":{\"file\":\"Sowi/Europäische Union - Phasen.md\",\"mode\":\"source\",\"backlinks\":true,\"source\":false}}",
                  "eState": "{\"cursor\":{\"from\":{\"line\":0,\"ch\":0},\"to\":{\"line\":0,\"ch\":0}}}"
                },
                {
                  "title": "Eintritt des Westbalkans in die EU",
                  "icon": "lucide-file",
                  "state": "{\"type\":\"markdown\",\"state\":{\"file\":\"Sowi/Eintritt des Westbalkans in die EU.md\",\"mode\":\"source\",\"backlinks\":true,\"source\":false}}",
                  "eState": "{\"cursor\":{\"from\":{\"line\":0,\"ch\":0},\"to\":{\"line\":0,\"ch\":0}}}"
                },
                {
                  "title": "Europäische Gemeinschaft für Kohle und Stahl",
                  "icon": "lucide-file",
                  "state": "{\"type\":\"markdown\",\"state\":{\"file\":\"Sowi/Europäische Gemeinschaft für Kohle und Stahl.md\",\"mode\":\"source\",\"backlinks\":true,\"source\":false}}",
                  "eState": "{\"cursor\":{\"from\":{\"line\":0,\"ch\":0},\"to\":{\"line\":0,\"ch\":0}}}"
                },
                {
                  "title": "Europäische Verteidigungsgemeinschaft",
                  "icon": "lucide-file",
                  "state": "{\"type\":\"markdown\",\"state\":{\"file\":\"Sowi/Europäische Verteidigungsgemeinschaft.md\",\"mode\":\"source\",\"backlinks\":true,\"source\":false}}",
                  "eState": "{\"cursor\":{\"from\":{\"line\":0,\"ch\":0},\"to\":{\"line\":0,\"ch\":0}}}"
                },
                {
                  "title": "Europäische Atomgemeinschaft",
                  "icon": "lucide-file",
                  "state": "{\"type\":\"markdown\",\"state\":{\"file\":\"Sowi/Europäische Atomgemeinschaft.md\",\"mode\":\"source\",\"backlinks\":true,\"source\":false}}",
                  "eState": "{\"cursor\":{\"from\":{\"line\":0,\"ch\":0},\"to\":{\"line\":0,\"ch\":0}}}"
                },
                {
                  "title": "Europäische Gemeinschaft",
                  "icon": "lucide-file",
                  "state": "{\"type\":\"markdown\",\"state\":{\"file\":\"Sowi/Europäische Gemeinschaft.md\",\"mode\":\"source\",\"backlinks\":true,\"source\":false}}",
                  "eState": "{\"cursor\":{\"from\":{\"line\":0,\"ch\":0},\"to\":{\"line\":0,\"ch\":0}}}"
                },
                {
                  "title": "Benelux",
                  "icon": "lucide-file",
                  "state": "{\"type\":\"markdown\",\"state\":{\"file\":\"Sowi/Benelux.md\",\"mode\":\"source\",\"backlinks\":true,\"source\":false}}",
                  "eState": "{\"cursor\":{\"from\":{\"line\":0,\"ch\":0},\"to\":{\"line\":0,\"ch\":0}}}"
                },
                {
                  "title": "Europäische Atomgemeinschaft",
                  "icon": "lucide-file",
                  "state": "{\"type\":\"markdown\",\"state\":{\"file\":\"Sowi/Europäische Atomgemeinschaft.md\",\"mode\":\"source\",\"backlinks\":true,\"source\":false}}",
                  "eState": "{\"cursor\":{\"from\":{\"line\":0,\"ch\":0},\"to\":{\"line\":0,\"ch\":0}}}"
                },
                {
                  "title": "Europäische Wirtschaftsgemeinschaft",
                  "icon": "lucide-file",
                  "state": "{\"type\":\"markdown\",\"state\":{\"file\":\"Sowi/Europäische Wirtschaftsgemeinschaft.md\",\"mode\":\"source\",\"backlinks\":true,\"source\":false}}",
                  "eState": "{\"cursor\":{\"from\":{\"line\":0,\"ch\":0},\"to\":{\"line\":0,\"ch\":0}}}"
                },
                {
                  "title": "Europäisches Währungssystem",
                  "icon": "lucide-file",
                  "state": "{\"type\":\"markdown\",\"state\":{\"file\":\"Sowi/Europäisches Währungssystem.md\",\"mode\":\"source\",\"backlinks\":true,\"source\":false}}",
                  "eState": "{\"cursor\":{\"from\":{\"line\":0,\"ch\":0},\"to\":{\"line\":0,\"ch\":0}}}"
                },
                {
                  "title": "Geschichte der EU",
                  "icon": "lucide-file",
                  "state": "{\"type\":\"markdown\",\"state\":{\"file\":\"Sowi/Geschichte der EU.md\",\"mode\":\"source\",\"backlinks\":true,\"source\":false}}",
                  "eState": "{\"cursor\":{\"from\":{\"line\":0,\"ch\":0},\"to\":{\"line\":0,\"ch\":0}}}"
                },
                {
                  "title": "Einheitliche Europäische Akte",
                  "icon": "lucide-file",
                  "state": "{\"type\":\"markdown\",\"state\":{\"file\":\"Sowi/Einheitliche Europäische Akte.md\",\"mode\":\"source\",\"backlinks\":true,\"source\":false}}",
                  "eState": "{\"cursor\":{\"from\":{\"line\":0,\"ch\":0},\"to\":{\"line\":0,\"ch\":0}}}"
                },
                {
                  "title": "Gemeinsame Außen- und Sicherheitspolitik",
                  "icon": "lucide-file",
                  "state": "{\"type\":\"markdown\",\"state\":{\"file\":\"Sowi/Gemeinsame Außen- und Sicherheitspolitik.md\",\"mode\":\"source\",\"backlinks\":true,\"source\":false}}",
                  "eState": "{\"cursor\":{\"from\":{\"line\":0,\"ch\":0},\"to\":{\"line\":0,\"ch\":0}}}"
                },
                {
                  "title": "Europäische Wirtschafts- und Währungsunion",
                  "icon": "lucide-file",
                  "state": "{\"type\":\"markdown\",\"state\":{\"file\":\"Sowi/Europäische Wirtschafts- und Währungsunion.md\",\"mode\":\"source\",\"backlinks\":true,\"source\":false}}",
                  "eState": "{\"cursor\":{\"from\":{\"line\":0,\"ch\":0},\"to\":{\"line\":0,\"ch\":0}}}"
                },
                {
                  "title": "Europäischer Rat",
                  "icon": "lucide-file",
                  "state": "{\"type\":\"markdown\",\"state\":{\"file\":\"Sowi/Europäischer Rat.md\",\"mode\":\"source\",\"backlinks\":true,\"source\":false}}",
                  "eState": "{\"cursor\":{\"from\":{\"line\":0,\"ch\":0},\"to\":{\"line\":0,\"ch\":0}}}"
                },
                {
                  "title": "Europäisches Parlament",
                  "icon": "lucide-file",
                  "state": "{\"type\":\"markdown\",\"state\":{\"file\":\"Sowi/Europäisches Parlament.md\",\"mode\":\"source\",\"backlinks\":true,\"source\":false}}",
                  "eState": "{\"cursor\":{\"from\":{\"line\":0,\"ch\":0},\"to\":{\"line\":0,\"ch\":0}}}"
                },
                {
                  "title": "Europäische Union",
                  "icon": "lucide-file",
                  "state": "{\"type\":\"markdown\",\"state\":{\"file\":\"Sowi/Europäische Union.md\",\"mode\":\"source\",\"backlinks\":true,\"source\":false}}",
                  "eState": "{\"cursor\":{\"from\":{\"line\":0,\"ch\":0},\"to\":{\"line\":0,\"ch\":0}}}"
                },
                {
                  "title": "Europäisches Parlament",
                  "icon": "lucide-file",
                  "state": "{\"type\":\"markdown\",\"state\":{\"file\":\"Sowi/Europäisches Parlament.md\",\"mode\":\"source\",\"backlinks\":true,\"source\":false}}",
                  "eState": "{\"cursor\":{\"from\":{\"line\":0,\"ch\":0},\"to\":{\"line\":0,\"ch\":0}}}"
                },
                {
                  "title": "Gerichtshof der Europäischen Union",
                  "icon": "lucide-file",
                  "state": "{\"type\":\"markdown\",\"state\":{\"file\":\"Sowi/Gerichtshof der Europäischen Union.md\",\"mode\":\"source\",\"backlinks\":true,\"source\":false}}",
                  "eState": "{\"cursor\":{\"from\":{\"line\":0,\"ch\":0},\"to\":{\"line\":0,\"ch\":0}},\"scroll\":0}"
                },
                {
                  "state": "{}",
                  "eState": "{}"
                },
                {
                  "title": "Europäisches Parlament",
                  "icon": "lucide-file",
                  "state": "{\"type\":\"markdown\",\"state\":{\"file\":\"Sowi/Europäisches Parlament.md\",\"mode\":\"source\",\"backlinks\":true,\"source\":false}}",
                  "eState": "{\"cursor\":{\"from\":{\"line\":0,\"ch\":0},\"to\":{\"line\":0,\"ch\":0}}}"
                },
                {
                  "title": "Europäische Union",
                  "icon": "lucide-file",
                  "state": "{\"type\":\"markdown\",\"state\":{\"file\":\"Sowi/Europäische Union.md\",\"mode\":\"source\",\"backlinks\":true,\"source\":false}}",
                  "eState": "{\"cursor\":{\"from\":{\"line\":0,\"ch\":0},\"to\":{\"line\":0,\"ch\":0}}}"
                },
                {
                  "title": "Europäischer Rat",
                  "icon": "lucide-file",
                  "state": "{\"type\":\"markdown\",\"state\":{\"file\":\"Sowi/Europäischer Rat.md\",\"mode\":\"source\",\"backlinks\":true,\"source\":false}}",
                  "eState": "{\"cursor\":{\"from\":{\"line\":0,\"ch\":0},\"to\":{\"line\":0,\"ch\":0}}}"
                },
                {
                  "title": "Europäische Union",
                  "icon": "lucide-file",
                  "state": "{\"type\":\"markdown\",\"state\":{\"file\":\"Sowi/Europäische Union.md\",\"mode\":\"source\",\"backlinks\":true,\"source\":false}}",
                  "eState": "{\"cursor\":{\"from\":{\"line\":0,\"ch\":0},\"to\":{\"line\":0,\"ch\":0}}}"
                },
                {
                  "title": "Europäisches Parlament",
                  "icon": "lucide-file",
                  "state": "{\"type\":\"markdown\",\"state\":{\"file\":\"Sowi/Europäisches Parlament.md\",\"mode\":\"source\",\"backlinks\":true,\"source\":false}}",
                  "eState": "{\"cursor\":{\"from\":{\"line\":6,\"ch\":1},\"to\":{\"line\":6,\"ch\":1}}}"
                }
              ]
            },
            "state": {
              "type": "markdown",
              "state": {
                "file": "Sowi/Europäische Union.md",
                "mode": "source",
                "backlinks": true,
                "source": false
              }
            }
          },
          {
            "id": "a3207fb642d769c6",
            "type": "leaf",
            "pane-relief:history-v1": {
              "pos": 0,
              "stack": [
                {
                  "state": "{}",
                  "eState": "{}"
                }
              ]
            },
            "state": {
              "type": "markdown",
              "state": {
                "file": "Sowi/EU-Kommission.md",
                "mode": "source",
                "backlinks": true,
                "source": false
              }
            }
          },
          {
            "id": "d50356a5da657b7c",
            "type": "leaf",
            "pane-relief:history-v1": {
              "pos": 0,
              "stack": [
                {
                  "state": "{}",
                  "eState": "{}"
                }
              ]
            },
            "state": {
              "type": "markdown",
              "state": {
                "file": "Sowi/Gerichtshof der Europäischen Union.md",
                "mode": "source",
                "backlinks": true,
                "source": false
              }
            }
          }
        ],
        "currentTab": 1
      }
    ],
    "direction": "vertical"
  },
  "left": {
    "id": "4bf9c073a5d2f73f",
    "type": "split",
    "children": [
      {
        "id": "7628399c4b2927aa",
        "type": "tabs",
        "children": [
          {
            "id": "24908edbb09fe0ec",
            "type": "leaf",
            "pane-relief:history-v1": {
              "pos": 0,
              "stack": [
                {
                  "state": "{}",
                  "eState": "{}"
                }
              ]
            },
            "state": {
              "type": "file-explorer",
              "state": {
                "sortOrder": "byModifiedTime"
              }
            }
          },
          {
            "id": "3a0fa27586a89227",
            "type": "leaf",
            "pane-relief:history-v1": {
              "pos": 0,
              "stack": [
                {
                  "state": "{}",
                  "eState": "{}"
                }
              ]
            },
            "state": {
              "type": "bookmarks",
              "state": {}
            }
          },
          {
            "id": "262bd944cfdad646",
            "type": "leaf",
            "pane-relief:history-v1": {
              "pos": 0,
              "stack": [
                {
                  "state": "{}",
                  "eState": "{}"
                }
              ]
            },
            "state": {
              "type": "recent-files",
              "state": {}
            }
          },
          {
            "id": "0a828ee010dcd078",
            "type": "leaf",
            "pane-relief:history-v1": {
              "pos": 0,
              "stack": [
                {
                  "state": "{}",
                  "eState": "{}"
                }
              ]
            },
            "state": {
              "type": "search",
              "state": {
                "query": "mentalis",
                "matchingCase": false,
                "explainSearch": false,
                "collapseAll": false,
                "extraContext": false,
                "sortOrder": "alphabetical"
              }
            }
          }
        ]
      }
    ],
    "direction": "horizontal",
    "width": 317.5
  },
  "right": {
    "id": "ace585f8412eb6f6",
    "type": "split",
    "children": [
      {
        "id": "d4c3cee098077eeb",
        "type": "tabs",
        "children": [
          {
            "id": "7ac8fe17db6cf076",
            "type": "leaf",
            "pane-relief:history-v1": {
              "pos": 0,
              "stack": [
                {
                  "state": "{}",
                  "eState": "{}"
                }
              ]
            },
            "state": {
              "type": "backlink",
              "state": {
                "file": "Sowi/EU-Kommission.md",
                "collapseAll": false,
                "extraContext": false,
                "sortOrder": "alphabetical",
                "showSearch": false,
                "searchQuery": "",
                "backlinkCollapsed": false,
                "unlinkedCollapsed": true
              }
            }
          },
          {
            "id": "c396f1413cd8b683",
            "type": "leaf",
            "pane-relief:history-v1": {
              "pos": 0,
              "stack": [
                {
                  "state": "{}",
                  "eState": "{}"
                }
              ]
            },
            "state": {
              "type": "outgoing-link",
              "state": {
                "file": "Sowi/EU-Kommission.md",
                "linksCollapsed": false,
                "unlinkedCollapsed": true
              }
            }
          },
          {
            "id": "08eaafe7cbf8df99",
            "type": "leaf",
            "pane-relief:history-v1": {
              "pos": 0,
              "stack": [
                {
                  "state": "{}",
                  "eState": "{}"
                }
              ]
            },
            "state": {
              "type": "tag",
              "state": {
                "sortOrder": "frequency",
                "useHierarchy": true
              }
            }
          },
          {
            "id": "8847df7c55d6e099",
            "type": "leaf",
            "pane-relief:history-v1": {
              "pos": 0,
              "stack": [
                {
                  "state": "{}",
                  "eState": "{}"
                }
              ]
            },
            "state": {
              "type": "outline",
              "state": {
                "file": "Sowi/EU-Kommission.md"
              }
            }
          },
          {
            "id": "520ad1919bc431dc",
            "type": "leaf",
            "pane-relief:history-v1": {
              "pos": 0,
              "stack": [
                {
                  "state": "{}",
                  "eState": "{}"
                }
              ]
            },
            "state": {
              "type": "calendar",
              "state": {}
            }
          },
          {
            "id": "fd8dc67ba101b189",
            "type": "leaf",
            "pane-relief:history-v1": {
              "pos": 0,
              "stack": [
                {
                  "state": "{}",
                  "eState": "{}"
                }
              ]
            },
            "state": {
              "type": "all-properties",
              "state": {
                "sortOrder": "frequency"
              }
            }
          }
        ]
      }
    ],
    "direction": "horizontal",
    "width": 300,
    "collapsed": true
  },
  "left-ribbon": {
    "hiddenItems": {
      "markdown-importer:Open format converter": false,
      "random-note:Open random note": false,
      "workspaces:Manage workspace layouts": false,
      "omnisearch:Omnisearch": false,
      "switcher:Open quick switcher": false,
      "graph:Open graph view": false,
      "canvas:Create new canvas": false,
      "daily-notes:Open today's daily note": false,
      "templates:Insert template": false,
      "command-palette:Open command palette": false,
      "periodic-notes:Open today's daily note": false
    }
  },
  "active": "a3207fb642d769c6",
  "lastOpenFiles": [
    "Sowi/Europäisches Parlament.md",
    "Sowi/EU-Kommission.md",
    "Sowi/Europäische Union.md",
    "Sowi/Europäische Gemeinschaft für Kohle und Stahl.md",
    "Sowi/Eintritt des Westbalkans in die EU.md",
    "Sowi/Europäische Union - Phasen.md",
    "Sowi/Rat der Europäischen Union (Ministerrat).md",
    "Sowi/Gerichtshof der Europäischen Union.md",
    "Sowi/Europäischer Rat.md",
    "Europäischen Union.md",
    "Sowi/Europäische Union - Friedensnobelpreis.md",
    "Sowi/Europäische Verteidigungsgemeinschaft.md",
    "Sowi/Europäische Atomgemeinschaft.md",
    "Sowi/Europäische Gemeinschaft.md",
    "Sowi/Benelux.md",
    "Sowi/Europäische Wirtschaftsgemeinschaft.md",
    "Sowi/Europäisches Währungssystem.md",
    "Sowi/Geschichte der EU.md",
    "Sowi/Einheitliche Europäische Akte.md",
    "Sowi/Gemeinsame Außen- und Sicherheitspolitik.md",
    "Sowi/Europäische Wirtschafts- und Währungsunion.md",
    "Deutsch/Fachbegriffe der Linguistik.md",
    "Deutsch/Theorie von Steven Pinker.md",
    "Coding/Backpropagation.md",
    "Coding/NNUE.md",
    "Coding/Fourier transform.md",
    "Math/735310_Stochastik_Normalverteilung_und_Sigma_Regeln.pdf",
    "Misc",
    "Coding/807_on_the_convergence_of_adam_and.pdf",
    "Coding/Nicht bestätigt 291095.crdownload",
    "Deutsch",
    "Phonetik",
    "Nativismus",
    "1111100000.txt",
    "1111100000_.txt",
    "Untitled.txt",
    "Untitled.canvas",
    "Pasted image 20230807163024.png",
    "Pasted image 20230807163023.png",
    "Pasted image 20230716151717.png",
    "Pasted image 20230716151700.png",
    "Pasted image 20230716151657.png"
  ]
}